icpp/__init__.py
icpp/__main__.py
icpp/py.typed
icpp/version.py
icpp-2.1.0.dist-info/METADATA
icpp-2.1.0.dist-info/WHEEL
icpp-2.1.0.dist-info/entry_points.txt
icpp-2.1.0.dist-info/top_level.txt
icpp-2.1.0.dist-info/RECORD
